LICENCE
setup.py
py_partner_api/PartnerAPI.py
py_partner_api/__init__.py
py_partner_api/models.py
py_partner_api.egg-info/PKG-INFO
py_partner_api.egg-info/SOURCES.txt
py_partner_api.egg-info/dependency_links.txt
py_partner_api.egg-info/requires.txt
py_partner_api.egg-info/top_level.txt
py_partner_api/cache/__init__.py
py_partner_api/cache/data_cache.py
py_partner_api/cache/memory_cache.py
py_partner_api/cache/redis.py