Metadata-Version: 2.1
Name: py-partner-api
Version: 1.1.0
Summary: Simple work with partner
Home-page: 
Author: DPhascow
Author-email: d.sinisterpsychologist@gmail.com
Keywords: partner,smm
Platform: any
License-File: LICENCE
